LICENSE.txt
README.md
setup.py
scurvysin/__init__.py
scurvysin/cli.py
scurvysin/get_pip_deps.py
scurvysin.egg-info/PKG-INFO
scurvysin.egg-info/SOURCES.txt
scurvysin.egg-info/dependency_links.txt
scurvysin.egg-info/entry_points.txt
scurvysin.egg-info/top_level.txt