Metadata-Version: 1.2
Name: scurvysin
Version: 2021.0
Summary: Pip & conda wrapper / warper.
Home-page: https://github.com/pythomec/scurvysin
Author: Jan Pipek, Pavel Cahyna
Author-email: jan.pipek@gmail.com
License: MIT
Platform: UNKNOWN
Classifier: Development Status :: 3 - Alpha
Classifier: License :: OSI Approved :: MIT License
Requires-Python: ~=3.6
